kaymo/__init__.py
kaymo-0.1.dist-info/LICENSE
kaymo-0.1.dist-info/METADATA
kaymo-0.1.dist-info/WHEEL
kaymo-0.1.dist-info/top_level.txt
kaymo-0.1.dist-info/RECORD
