Metadata-Version: 2.1
Name: kaymo
Version: 0.1
Summary: Facial and Speech Emotion Recognition 🔊💗👀🎭🎶
Home-page: https://github.com/amrmkayid/kaymo
Author: Amr Kayid
Author-email: amrkayid2027@gmail.com
License: UNKNOWN
Platform: UNKNOWN
Classifier: Programming Language :: Python :: 3
Classifier: License :: OSI Approved :: MIT License
Classifier: Operating System :: OS Independent
